MANIFEST.in
setup.cfg
setup.py
securitas.egg-info/PKG-INFO
securitas.egg-info/SOURCES.txt
securitas.egg-info/dependency_links.txt
securitas.egg-info/requires.txt
securitas.egg-info/top_level.txt
symantec_package/HTTPHandler.py
symantec_package/__init__.py
symantec_package/lib/__init__.py
symantec_package/lib/allServices/SymantecServices.py
symantec_package/lib/allServices/__init__.py
symantec_package/lib/legacyService/SymantecLegacyServices.py
symantec_package/lib/legacyService/__init__.py
symantec_package/lib/managementService/SymantecManagementServices.py
symantec_package/lib/managementService/__init__.py
symantec_package/lib/queryService/SymantecQueryServices.py
symantec_package/lib/queryService/__init__.py
symantec_package/lib/userService/SymantecUserServices.py
symantec_package/lib/userService/__init__.py
symantec_package/test/TestAuthentication.py
symantec_package/test/TestMultipleServicesFunctions.py
symantec_package/test/TestQuerying.py
symantec_package/test/TestUserManagement.py
symantec_package/wsdl_files/vip_auth.wsdl
symantec_package/wsdl_files/vip_auth.xsd
symantec_package/wsdl_files/vip_common_auth.xsd
symantec_package/wsdl_files/vipuserservices-1.7.xsd
symantec_package/wsdl_files/vipuserservices-auth-1.7.wsdl
symantec_package/wsdl_files/vipuserservices-mgmt-1.7.wsdl
symantec_package/wsdl_files/vipuserservices-query-1.7.wsdl