Metadata-Version: 1.1
Name: securitas
Version: 1.0.1
Summary: Python SDK to increase productivity and ease implementation of Symantec Validation and ID Protection (VIP) which is a two factor authentication API
Home-page: https://github.com/ArrenH/Securitas
Author: Allen Huynh, Gabriel Morcote, Hanlin Ye
Author-email: UNKNOWN
License: UNKNOWN
Download-URL: https://github.com/ArrenH/Securitas/archive/v1.0.tar.gz
Keywords: Symantec,VIP,Python,SOAP,Validation and Identity Protection,2FA,two factor authentication
Platform: UNKNOWN
